sysopswork/__init__.py
sysopswork/sysopswork.py
sysopswork-0.1.0.dist-info/METADATA
sysopswork-0.1.0.dist-info/WHEEL
sysopswork-0.1.0.dist-info/licenses/LICENSE
sysopswork-0.1.0.dist-info/RECORD
