Metadata-Version: 2.4
Name: sysopswork
Version: 0.1.0
Summary: SysOpsWork Automation supporting package
Project-URL: Homepage, https://github.com/sysopswork/sysopswork-python
Project-URL: Issues, https://github.com/sysopswork/sysopswork-python/issues
Author-email: Rodrigo Silva <rodrigo.silva@sysopswork.com>
License: Apache-2.0
License-File: LICENSE
Classifier: Operating System :: OS Independent
Classifier: Programming Language :: Python :: 3
Requires-Python: >=3.9
